fastbt/Meta.py
fastbt/__init__.py
fastbt/app.py
fastbt/datasource.py
fastbt/experimental.py
fastbt/features.py
fastbt/loaders.py
fastbt/metrics.py
fastbt/plotting.py
fastbt/rapid.py
fastbt/simulation.py
fastbt/tradebook.py
fastbt/urlpatterns.py
fastbt/utils.py
fastbt/brokers/__init__.py
fastbt/brokers/api.yaml
fastbt/brokers/fivepaisa.py
fastbt/brokers/fivepaisa.yaml
fastbt/brokers/fyers.py
fastbt/brokers/fyers.yaml
fastbt/brokers/master_trust.py
fastbt/brokers/master_trust.yaml
fastbt/brokers/spec.yaml
fastbt/brokers/zerodha.py
fastbt/brokers/zerodha.yaml
fastbt/files/IndexConstituents.xlsx
fastbt/files/__init__.py
fastbt/files/sectors.csv
fastbt/models/base.py
fastbt/models/breakout.py
fastbt/options/backtest.py
fastbt/options/order.py
fastbt/options/payoff.py
fastbt/options/store.py
fastbt/options/utils.py
fastbt/options/.mypy_cache/.gitignore
fastbt/options/.mypy_cache/CACHEDIR.TAG
fastbt/options/.mypy_cache/missing_stubs
fastbt/options/.mypy_cache/3.9/@plugins_snapshot.json
fastbt/options/.mypy_cache/3.9/__future__.data.json
fastbt/options/.mypy_cache/3.9/__future__.meta.json
fastbt/options/.mypy_cache/3.9/__main__.data.json
fastbt/options/.mypy_cache/3.9/__main__.meta.json
fastbt/options/.mypy_cache/3.9/_ast.data.json
fastbt/options/.mypy_cache/3.9/_ast.meta.json
fastbt/options/.mypy_cache/3.9/_bisect.data.json
fastbt/options/.mypy_cache/3.9/_bisect.meta.json
fastbt/options/.mypy_cache/3.9/_codecs.data.json
fastbt/options/.mypy_cache/3.9/_codecs.meta.json
fastbt/options/.mypy_cache/3.9/_collections_abc.data.json
fastbt/options/.mypy_cache/3.9/_collections_abc.meta.json
fastbt/options/.mypy_cache/3.9/_compression.data.json
fastbt/options/.mypy_cache/3.9/_compression.meta.json
fastbt/options/.mypy_cache/3.9/_csv.data.json
fastbt/options/.mypy_cache/3.9/_csv.meta.json
fastbt/options/.mypy_cache/3.9/_ctypes.data.json
fastbt/options/.mypy_cache/3.9/_ctypes.meta.json
fastbt/options/.mypy_cache/3.9/_curses.data.json
fastbt/options/.mypy_cache/3.9/_curses.meta.json
fastbt-0.6.0.dist-info/AUTHORS.rst
fastbt-0.6.0.dist-info/LICENSE
fastbt-0.6.0.dist-info/METADATA
fastbt-0.6.0.dist-info/WHEEL
fastbt-0.6.0.dist-info/top_level.txt
fastbt-0.6.0.dist-info/RECORD
