Metadata-Version: 2.1
Name: fastbt
Version: 0.6.0
Summary: A simple framework for fast and dirty backtesting
Home-page: https://github.com/uberdeveloper/fastbt
Author: UM
Author-email: uberdeveloper001@gmail.com
License: MIT license
Keywords: fastbt,backtesting,algorithmic trading,quantitative finance,research,finance
Classifier: Development Status :: 3 - Alpha
Classifier: Intended Audience :: Financial and Insurance Industry
Classifier: License :: OSI Approved :: MIT License
Classifier: Operating System :: OS Independent
Classifier: Programming Language :: Python
Classifier: Programming Language :: Python :: 3.7
Classifier: Programming Language :: Python :: 3.9
Classifier: Programming Language :: Python :: Implementation :: CPython
Classifier: Topic :: Office/Business :: Financial :: Investment
License-File: LICENSE
License-File: AUTHORS.rst
Requires-Dist: pandas (>=1.0.0)
Requires-Dist: sqlalchemy (<=2.0.0)
Requires-Dist: pendulum (>=2.0.0)
Provides-Extra: apps
Requires-Dist: streamlit (>1.15.0) ; extra == 'apps'
Provides-Extra: compiled
Requires-Dist: numba (>0.55.0) ; extra == 'compiled'
Provides-Extra: io
Requires-Dist: tables ; extra == 'io'
Requires-Dist: zarr ; extra == 'io'
Requires-Dist: openpyxl ; extra == 'io'
Requires-Dist: xlwt ; extra == 'io'
Provides-Extra: options
Requires-Dist: pydantic ; extra == 'options'
Provides-Extra: plotting
Requires-Dist: bokeh (>3.0.0) ; extra == 'plotting'
Provides-Extra: ta
Requires-Dist: TA-Lib ; extra == 'ta'
Provides-Extra: test
Requires-Dist: pytest ; extra == 'test'
Requires-Dist: pytest-watch ; extra == 'test'
Requires-Dist: ruff ; extra == 'test'
